{
  "dashboard": {
    "title": "Database Performance",
    "tags": ["database", "performance"],
    "timezone": "browser",
    "schemaVersion": 27,
    "version": 1,
    "refresh": "30s",
    "panels": [
      {
        "id": 1,
        "title": "PostgreSQL Connections",
        "type": "graph",
        "targets": [
          {
            "expr": "pg_stat_database_numbackends",
            "legendFormat": "Connections"
          }
        ],
        "gridPos": {"h": 8, "w": 12, "x": 0, "y": 0}
      },
      {
        "id": 2,
        "title": "PostgreSQL Replication Lag",
        "type": "graph",
        "targets": [
          {
            "expr": "pg_replication_lag_seconds",
            "legendFormat": "Lag (seconds)"
          }
        ],
        "gridPos": {"h": 8, "w": 12, "x": 12, "y": 0}
      },
      {
        "id": 3,
        "title": "Redis Memory Usage",
        "type": "graph",
        "targets": [
          {
            "expr": "redis_memory_used_bytes / redis_memory_max_bytes",
            "legendFormat": "Memory Usage %"
          }
        ],
        "gridPos": {"h": 8, "w": 12, "x": 0, "y": 8}
      },
      {
        "id": 4,
        "title": "Redis Connections",
        "type": "stat",
        "targets": [
          {
            "expr": "redis_connected_clients",
            "legendFormat": "Connections"
          }
        ],
        "gridPos": {"h": 4, "w": 6, "x": 12, "y": 8}
      }
    ]
  }
}



